[ 
    {
       "_id": "5c4fac61b3dc30b559d7fded",
       "firstName": "Roger",
       "lastName": "Reynolds",
       "email": "abc@gmail.com",
       "homeResortArea": "SnowBird",
       "experienceLevel": "Pro",
       "sessionLength": 6
   },

   {
    "_id": "5c4fac61b3dc30b559d0fdad",
    "firstName": "Derrick",
    "lastName": "foss",
    "email": "abc@gmail.com",
    "homeResortArea": "SnowBird",
    "experienceLevel": "Pro",
    "sessionLength": 6
},

{
    "_id": "5c4fac61b3dc30b559d0fded",
    "firstName": "Lacey",
    "lastName": "Em",
    "email": "abc@gmail.com",
    "homeResortArea": "SnowBird",
    "experienceLevel": "Pro",
    "sessionLength": 6
}
   
]